config/droids/bb.yml
config/droids/r2.yml
config/personalities/first_order_black.yml
config/personalities/resistance_blue.yml
config/personalities/smuggler_blue.yml
libastromech/__init__.py
libastromech/astromech.py
libastromech/bb.py
libastromech/r2.py
libastromech-1.0.0.dist-info/licenses/LICENSE
samples/bb.py
samples/beep.py
samples/discover_sounds.py
samples/keep_alive.py
samples/r2.py
libastromech-1.0.0.dist-info/METADATA
libastromech-1.0.0.dist-info/WHEEL
libastromech-1.0.0.dist-info/top_level.txt
libastromech-1.0.0.dist-info/RECORD
