Metadata-Version: 2.4
Name: libastromech
Version: 1.0.0
Summary: A Python library for interfacing with Galaxy's Edge Astromech Droids
Author-email: Phil McGachey <mcgachey@gmail.com>
License: MIT License
Project-URL: Homepage, https://github.com/mcgachey/libastromech
Keywords: droid,astromech
Classifier: License :: OSI Approved :: MIT License
Classifier: Programming Language :: Python
Classifier: Programming Language :: Python :: 3
Requires-Python: >=3.9
License-File: LICENSE
Requires-Dist: bleak>=0.22.3
Requires-Dist: PyYAML>=6.0.2
Dynamic: license-file
